pantsbuild.pants.contrib.python.checks-1.29.0-py3.6-nspkg.pth
pants/contrib/python/checks/register.py
pants/contrib/python/checks/tasks/__init__.py
pants/contrib/python/checks/tasks/python_eval.py
pants/contrib/python/checks/tasks/python_eval_subsystem.py
pants/contrib/python/checks/tasks/checkstyle/__init__.py
pants/contrib/python/checks/tasks/checkstyle/checkstyle.py
pants/contrib/python/checks/tasks/checkstyle/plugin_subsystem_base.py
pants/contrib/python/checks/tasks/checkstyle/pycheck_subsystem.py
pants/contrib/python/checks/tasks/checkstyle/pycodestyle_subsystem.py
pants/contrib/python/checks/tasks/checkstyle/pyflakes_subsystem.py
pants/contrib/python/checks/tasks/templates/python_eval/eval.py.mustache
pantsbuild.pants.contrib.python.checks-1.29.0.dist-info/METADATA
pantsbuild.pants.contrib.python.checks-1.29.0.dist-info/RECORD
pantsbuild.pants.contrib.python.checks-1.29.0.dist-info/WHEEL
pantsbuild.pants.contrib.python.checks-1.29.0.dist-info/entry_points.txt
pantsbuild.pants.contrib.python.checks-1.29.0.dist-info/namespace_packages.txt
pantsbuild.pants.contrib.python.checks-1.29.0.dist-info/top_level.txt
pantsbuild.pants.contrib.python.checks-1.29.0.dist-info/zip-safe
