Metadata-Version: 2.1
Name: pantsbuild.pants.contrib.python.checks
Version: 1.29.0
Summary: Additional python lints and checks.
Home-page: https://github.com/pantsbuild/pants
License: Apache License, Version 2.0
Project-URL: Documentation, https://www.pantsbuild.org/
Project-URL: Source, https://github.com/pantsbuild/pants
Project-URL: Tracker, https://github.com/pantsbuild/pants/issues
Platform: UNKNOWN
Classifier: Intended Audience :: Developers
Classifier: License :: OSI Approved :: Apache Software License
Classifier: Operating System :: MacOS :: MacOS X
Classifier: Operating System :: POSIX :: Linux
Classifier: Programming Language :: Python
Classifier: Topic :: Software Development :: Build Tools
Requires-Dist: pantsbuild.pants.contrib.python.checks.checker (==1.29.0)
Requires-Dist: pantsbuild.pants (==1.29.0)
Requires-Dist: pex (==2.1.11)
